{
  "vocabulary": [
    { "word": "<strong>barrio</strong>", "definition": "a neighborhood, especially in a Spanish-speaking community (barrio)" },
    { "word": "<strong>soccer</strong>", "definition": "a sport played with a round ball and goals (fútbol)" },
    { "word": "<strong>neighborhood</strong>", "definition": "a local area where people live (vecindario)" },
    { "word": "<strong>cancha</strong>", "definition": "a sports field or court (cancha)" },
    { "word": "<strong>field</strong>", "definition": "an open area of land for playing sports (campo)" },
    { "word": "<strong>kick</strong>", "definition": "to strike something with the foot (patear)" },
    { "word": "<strong>fence</strong>", "definition": "a barrier enclosing an area (cerca)" },
    { "word": "<strong>street</strong>", "definition": "a public road in a city or town (calle)" },
    { "word": "<strong>motorcycle</strong>", "definition": "a two-wheeled motor vehicle (motocicleta)" },
    { "word": "<strong>corner</strong>", "definition": "the place where two streets meet (esquina)" },
    { "word": "<strong>shout</strong>", "definition": "to speak loudly or yell (gritar)" },
    { "word": "<strong>careful</strong>", "definition": "paying attention to avoid danger (cuidadoso)" }
  ]
}
